akshatx15/__init__.py
akshatx15/project_paths.json
akshatx15/project_paths.py
akshatx15-2.1.0.dist-info/METADATA
akshatx15-2.1.0.dist-info/WHEEL
akshatx15-2.1.0.dist-info/top_level.txt
akshatx15-2.1.0.dist-info/RECORD
