Metadata-Version: 2.1
Name: akshatx15
Version: 2.1.0
Summary: Project & Project Path Management library.
Author: Akshat Gupta
Author-email: akshat.gupta@involead.com
Classifier: Programming Language :: Python :: 3
Classifier: License :: OSI Approved :: MIT License
Classifier: Operating System :: OS Independent
Requires-Python: >=3
